pyDBMS/__init__.py
pyDBMS/dbtype.py
pydb/__init__.py
pydb/dbtype.py
pyDBMS-0.1.3.dist-info/LICENSE
pyDBMS-0.1.3.dist-info/METADATA
pyDBMS-0.1.3.dist-info/WHEEL
pyDBMS-0.1.3.dist-info/top_level.txt
pyDBMS-0.1.3.dist-info/RECORD
