Metadata-Version: 2.1
Name: pyDBMS
Version: 0.1.3
Summary: Easy to use, light weight ORM
Home-page: https://github.com/JacksonDorsett/pydb
Author: Jackson Dorsett
Author-email: dorsettj@gmail.com
License: MIT
Platform: UNKNOWN
Classifier: License :: OSI Approved :: MIT License
Classifier: Programming Language :: Python :: 3
Classifier: Programming Language :: Python :: 3.7
